finchlite/__init__.py
finchlite/algebra/__init__.py
finchlite/algebra/algebra.py
finchlite/algebra/operator.py
finchlite/algebra/tensor.py
finchlite/autoschedule/__init__.py
finchlite/autoschedule/_utils.py
finchlite/autoschedule/compiler.py
finchlite/autoschedule/executor.py
finchlite/autoschedule/optimize.py
finchlite/codegen/__init__.py
finchlite/codegen/c.py
finchlite/codegen/numba_backend.py
finchlite/codegen/numpy_buffer.py
finchlite/compile/__init__.py
finchlite/compile/bufferized_ndarray.py
finchlite/compile/looplets.py
finchlite/compile/lower.py
finchlite/finch_assembly/__init__.py
finchlite/finch_assembly/buffer.py
finchlite/finch_assembly/dev_doc.md
finchlite/finch_assembly/interpreter.py
finchlite/finch_assembly/nodes.py
finchlite/finch_assembly/struct.py
finchlite/finch_assembly/type_checker.py
finchlite/finch_logic/__init__.py
finchlite/finch_logic/interpreter.py
finchlite/finch_logic/nodes.py
finchlite/finch_notation/__init__.py
finchlite/finch_notation/interpreter.py
finchlite/finch_notation/nodes.py
finchlite/galley/__init__.py
finchlite/galley/dc_stats.py
finchlite/galley/dense_stat.py
finchlite/galley/tensor_def.py
finchlite/galley/tensor_stats.py
finchlite/interface/__init__.py
finchlite/interface/eager.py
finchlite/interface/fuse.py
finchlite/interface/lazy.py
finchlite/interface/overrides.py
finchlite/interface/scalar.py
finchlite/symbolic/__init__.py
finchlite/symbolic/environment.py
finchlite/symbolic/ftype.py
finchlite/symbolic/gensym.py
finchlite/symbolic/rewriters.py
finchlite/symbolic/term.py
finchlite/tensor/__init__.py
finchlite/tensor/fiber_tensor.py
finchlite/tensor/level/__init__.py
finchlite/tensor/level/dense_level.py
finchlite/tensor/level/element_level.py
finchlite/util/__init__.py
finchlite/util/cache.py
finchlite/util/config.py
finchlite/util/print.py
finch_tensor_lite-0.1.0.dist-info/LICENSE
finch_tensor_lite-0.1.0.dist-info/METADATA
finch_tensor_lite-0.1.0.dist-info/WHEEL
finch_tensor_lite-0.1.0.dist-info/RECORD
